NodeCoder/__init__.py
NodeCoder/generate_graph_data.py
NodeCoder/predict.py
NodeCoder/preprocess_raw_data.py
NodeCoder/train.py
NodeCoder/featurizer/__init__.py
NodeCoder/featurizer/build_datasets.py
NodeCoder/featurizer/protein_features.py
NodeCoder/featurizer/protein_sequences.py
NodeCoder/featurizer/protein_tasks.py
NodeCoder/gcn/NodeCoder.py
NodeCoder/gcn/NodeCoder_predict.py
NodeCoder/gcn/NodeCoder_train.py
NodeCoder/gcn/__init__.py
NodeCoder/gcn/train_wrapper.py
NodeCoder/graph_generator/__init__.py
NodeCoder/graph_generator/clustering.py
NodeCoder/graph_generator/graph_data_generator.py
NodeCoder/graph_generator/protein_graph.py
NodeCoder/utilities/__init__.py
NodeCoder/utilities/config.py
NodeCoder/utilities/parser.py
NodeCoder/utilities/utils.py
NodeCoder-1.0.0.dist-info/LICENSE
NodeCoder-1.0.0.dist-info/METADATA
NodeCoder-1.0.0.dist-info/WHEEL
NodeCoder-1.0.0.dist-info/entry_points.txt
NodeCoder-1.0.0.dist-info/top_level.txt
NodeCoder-1.0.0.dist-info/RECORD
