Metadata-Version: 2.1
Name: NodeCoder
Version: 1.0.0
Summary: A PyTorch implementation of NodeCoder pipeline, a Graph Convolutional Network (GCN) framework for protein residue characterization.
Home-page: https://github.com/NasimAbdollahi/Nodecoder/
Author: Nasim Abdollahi
Author-email: nsm.abdolahi@gmail.com
License: MIT
Classifier: License :: OSI Approved :: MIT License
Classifier: Programming Language :: Python
Classifier: Programming Language :: Python :: 3
Classifier: Programming Language :: Python :: 3.8
Classifier: Programming Language :: Python :: Implementation :: CPython
Classifier: Programming Language :: Python :: Implementation :: PyPy
Requires-Python: >=3.8.5
License-File: LICENSE
Requires-Dist: scipy (>=1.5.4)
Requires-Dist: numpy (>=1.19.2)
Requires-Dist: pandas (>=1.1.5)
Requires-Dist: matplotlib (>=3.3.3)
Requires-Dist: torch (>=0.4.1)
Requires-Dist: torchvision (==0.8.1)
Requires-Dist: torchaudio (==0.7.0)
Requires-Dist: torch-scatter (==2.0.5)
Requires-Dist: torch-sparse (==0.6.8)
Requires-Dist: torch-cluster (==1.5.8)
Requires-Dist: torch-spline-conv (==1.2.0)
Requires-Dist: torch-geometric (==1.6.3)
Requires-Dist: scikit-learn (>=0.23.2)
Requires-Dist: texttable (>=1.6.3)
Requires-Dist: biopython (>=1.77)
Requires-Dist: freesasa (==2.0.5.post2)
Requires-Dist: loguru (>=0.6.0)
